{
    "title": "Getting Started",
    "description": "What is Linux? Get started on your journey with some history and context"
    "difficulty": "beginner",
    "time": "~25 minutes",
    "details": {
        "intro": {
            "text": "intro.md",
            "credits": "Created by [LinuxJourney.com](https://linuxjourney.com/) and adapted by [Tech Learning Collective](https://techlearningcollective.com/)."
        },
        "steps": [
            {
                "title": "Introductions",
                "text": "step1.md"
            }
        ],
        "finish": {
            "text": "finish.md"
        }
    },
    "environment": {
        "uilayout": "terminal"
    },
    "backend": {
        "imageid": "ubuntu"
    }
}
